<?xml version="1.0" encoding="Windows-1252"?>
<UserLog xmlns:xsi="http://www.w3.org/2001/XMLSchema-instance" xmlns:xsd="http://www.w3.org/2001/XMLSchema">
  <TotalTimeTakenToComplete>34.28</TotalTimeTakenToComplete>
  <TotalDistanceTraveled>71.195015</TotalDistanceTraveled>
  <MovementData>
    <Information>
      <idleTime>1.51839244</idleTime>
      <movement>
        <startPosition>
          <x>19.1</x>
          <y>0.9800001</y>
          <z>18</z>
        </startPosition>
        <endPosition>
          <x>17.5073872</x>
          <y>0.98</y>
          <z>17.8466072</z>
        </endPosition>
        <startTime>1.51839244</startTime>
        <endTime>1.83315969</endTime>
        <totalTime>0.314767241</totalTime>
        <distanceMoved>1.59998322</distanceMoved>
      </movement>
    </Information>
    <Information>
      <idleTime>10.4038658</idleTime>
      <movement>
        <startPosition>
          <x>16.1138325</x>
          <y>0.98</y>
          <z>17.7124233</z>
        </startPosition>
        <endPosition>
          <x>16.1232433</x>
          <y>0.98</y>
          <z>17.6128674</z>
        </endPosition>
        <startTime>12.2370253</startTime>
        <endTime>12.2535925</endTime>
        <totalTime>0.01656723</totalTime>
        <distanceMoved>0.09999978</distanceMoved>
      </movement>
    </Information>
    <Information>
      <idleTime>0</idleTime>
      <movement>
        <startPosition>
          <x>16.1232433</x>
          <y>0.98</y>
          <z>17.6128674</z>
        </startPosition>
        <endPosition>
          <x>16.1328278</x>
          <y>0.98</y>
          <z>17.5133266</z>
        </endPosition>
        <startTime>12.2535925</startTime>
        <endTime>12.2701588</endTime>
        <totalTime>0.0165662766</totalTime>
        <distanceMoved>0.100001067</distanceMoved>
      </movement>
    </Information>
    <Information>
      <idleTime>0</idleTime>
      <movement>
        <startPosition>
          <x>16.1328278</x>
          <y>0.98</y>
          <z>17.5133266</z>
        </startPosition>
        <endPosition>
          <x>16.1431065</x>
          <y>0.98</y>
          <z>17.4138565</z>
        </endPosition>
        <startTime>12.2701588</startTime>
        <endTime>12.286725</endTime>
        <totalTime>0.0165662766</totalTime>
        <distanceMoved>0.0999998</distanceMoved>
      </movement>
    </Information>
    <Information>
      <idleTime>0</idleTime>
      <movement>
        <startPosition>
          <x>16.1431065</x>
          <y>0.98</y>
          <z>17.4138565</z>
        </startPosition>
        <endPosition>
          <x>16.186306</x>
          <y>0.98</y>
          <z>17.0162</z>
        </endPosition>
        <startTime>12.286725</startTime>
        <endTime>12.36956</endTime>
        <totalTime>0.0828352</totalTime>
        <distanceMoved>0.399997</distanceMoved>
      </movement>
    </Information>
    <Information>
      <idleTime>0.397598267</idleTime>
      <movement>
        <startPosition>
          <x>16.3263931</x>
          <y>0.98</y>
          <z>16.5744629</z>
        </startPosition>
        <endPosition>
          <x>16.4098778</x>
          <y>0.98</y>
          <z>16.62951</z>
        </endPosition>
        <startTime>12.7671585</startTime>
        <endTime>12.7837257</endTime>
        <totalTime>0.01656723</totalTime>
        <distanceMoved>0.09999984</distanceMoved>
      </movement>
    </Information>
    <Information>
      <idleTime>0</idleTime>
      <movement>
        <startPosition>
          <x>16.4098778</x>
          <y>0.98</y>
          <z>16.62951</z>
        </startPosition>
        <endPosition>
          <x>16.4933624</x>
          <y>0.98</y>
          <z>16.6845589</z>
        </endPosition>
        <startTime>12.7837257</startTime>
        <endTime>12.8002939</endTime>
        <totalTime>0.0165681839</totalTime>
        <distanceMoved>0.09999984</distanceMoved>
      </movement>
    </Information>
    <Information>
      <idleTime>0</idleTime>
      <movement>
        <startPosition>
          <x>16.4933624</x>
          <y>0.98</y>
          <z>16.6845589</z>
        </startPosition>
        <endPosition>
          <x>16.66014</x>
          <y>0.98</y>
          <z>16.7949467</z>
        </endPosition>
        <startTime>12.8002939</startTime>
        <endTime>12.8499918</endTime>
        <totalTime>0.049697876</totalTime>
        <distanceMoved>0.199999809</distanceMoved>
      </movement>
    </Information>
    <Information>
      <idleTime>0</idleTime>
      <movement>
        <startPosition>
          <x>16.66014</x>
          <y>0.98</y>
          <z>16.7949467</z>
        </startPosition>
        <endPosition>
          <x>16.9856</x>
          <y>0.98</y>
          <z>17.0273075</z>
        </endPosition>
        <startTime>12.8499918</startTime>
        <endTime>12.932826</endTime>
        <totalTime>0.0828342438</totalTime>
        <distanceMoved>0.399895072</distanceMoved>
      </movement>
    </Information>
    <Information>
      <idleTime>0</idleTime>
      <movement>
        <startPosition>
          <x>16.9856</x>
          <y>0.98</y>
          <z>17.0273075</z>
        </startPosition>
        <endPosition>
          <x>17.068758</x>
          <y>0.98</y>
          <z>17.0828457</z>
        </endPosition>
        <startTime>12.932826</startTime>
        <endTime>12.9493923</endTime>
        <totalTime>0.0165662766</totalTime>
        <distanceMoved>0.09999912</distanceMoved>
      </movement>
    </Information>
    <Information>
      <idleTime>0</idleTime>
      <movement>
        <startPosition>
          <x>17.068758</x>
          <y>0.98</y>
          <z>17.0828457</z>
        </startPosition>
        <endPosition>
          <x>17.2426414</x>
          <y>0.98</y>
          <z>17.18157</z>
        </endPosition>
        <startTime>12.9493923</startTime>
        <endTime>12.9825268</endTime>
        <totalTime>0.03313446</totalTime>
        <distanceMoved>0.199954867</distanceMoved>
      </movement>
    </Information>
    <Information>
      <idleTime>0</idleTime>
      <movement>
        <startPosition>
          <x>17.2426414</x>
          <y>0.98</y>
          <z>17.18157</z>
        </startPosition>
        <endPosition>
          <x>17.5217533</x>
          <y>0.98</y>
          <z>17.2912388</z>
        </endPosition>
        <startTime>12.9825268</startTime>
        <endTime>13.0487928</endTime>
        <totalTime>0.06626606</totalTime>
        <distanceMoved>0.2998844</distanceMoved>
      </movement>
    </Information>
    <Information>
      <idleTime>0</idleTime>
      <movement>
        <startPosition>
          <x>17.5217533</x>
          <y>0.98</y>
          <z>17.2912388</z>
        </startPosition>
        <endPosition>
          <x>17.6168785</x>
          <y>0.98</y>
          <z>17.3220844</z>
        </endPosition>
        <startTime>13.0487928</startTime>
        <endTime>13.0653582</endTime>
        <totalTime>0.0165653229</totalTime>
        <distanceMoved>0.100001283</distanceMoved>
      </movement>
    </Information>
    <Information>
      <idleTime>0</idleTime>
      <movement>
        <startPosition>
          <x>17.6168785</x>
          <y>0.98</y>
          <z>17.3220844</z>
        </startPosition>
        <endPosition>
          <x>18.1065311</x>
          <y>0.98</y>
          <z>17.4199467</z>
        </endPosition>
        <startTime>13.0653582</startTime>
        <endTime>13.1647587</endTime>
        <totalTime>0.09940052</totalTime>
        <distanceMoved>0.499336272</distanceMoved>
      </movement>
    </Information>
    <Information>
      <idleTime>0</idleTime>
      <movement>
        <startPosition>
          <x>18.1065311</x>
          <y>0.98</y>
          <z>17.4199467</z>
        </startPosition>
        <endPosition>
          <x>18.6727962</x>
          <y>0.98</y>
          <z>17.6134872</z>
        </endPosition>
        <startTime>13.1647587</startTime>
        <endTime>13.2807255</endTime>
        <totalTime>0.1159668</totalTime>
        <distanceMoved>0.5984264</distanceMoved>
      </movement>
    </Information>
    <Information>
      <idleTime>0.8117666</idleTime>
      <movement>
        <startPosition>
          <x>19.8787346</x>
          <y>0.98</y>
          <z>18.3778</z>
        </startPosition>
        <endPosition>
          <x>19.5867081</x>
          <y>0.98</y>
          <z>18.4462948</z>
        </endPosition>
        <startTime>14.0924921</startTime>
        <endTime>14.1587591</endTime>
        <totalTime>0.06626701</totalTime>
        <distanceMoved>0.2999517</distanceMoved>
      </movement>
    </Information>
    <Information>
      <idleTime>0</idleTime>
      <movement>
        <startPosition>
          <x>19.5867081</x>
          <y>0.98</y>
          <z>18.4462948</z>
        </startPosition>
        <endPosition>
          <x>19.3885136</x>
          <y>0.98</y>
          <z>18.4730911</z>
        </endPosition>
        <startTime>14.1587591</startTime>
        <endTime>14.1918917</endTime>
        <totalTime>0.0331325531</totalTime>
        <distanceMoved>0.199997768</distanceMoved>
      </movement>
    </Information>
    <Information>
      <idleTime>0</idleTime>
      <movement>
        <startPosition>
          <x>19.3885136</x>
          <y>0.98</y>
          <z>18.4730911</z>
        </startPosition>
        <endPosition>
          <x>19.2891178</x>
          <y>0.98</y>
          <z>18.4840641</z>
        </endPosition>
        <startTime>14.1918917</startTime>
        <endTime>14.2084646</endTime>
        <totalTime>0.0165729523</totalTime>
        <distanceMoved>0.09999961</distanceMoved>
      </movement>
    </Information>
    <Information>
      <idleTime>0</idleTime>
      <movement>
        <startPosition>
          <x>19.2891178</x>
          <y>0.98</y>
          <z>18.4840641</z>
        </startPosition>
        <endPosition>
          <x>19.09023</x>
          <y>0.98</y>
          <z>18.5051441</z>
        </endPosition>
        <startTime>14.2084646</startTime>
        <endTime>14.2581587</endTime>
        <totalTime>0.04969406</totalTime>
        <distanceMoved>0.200000882</distanceMoved>
      </movement>
    </Information>
    <Information>
      <idleTime>0</idleTime>
      <movement>
        <startPosition>
          <x>19.09023</x>
          <y>0.98</y>
          <z>18.5051441</z>
        </startPosition>
        <endPosition>
          <x>18.990612</x>
          <y>0.98</y>
          <z>18.5138588</z>
        </endPosition>
        <startTime>14.2581587</startTime>
        <endTime>14.2747259</endTime>
        <totalTime>0.01656723</totalTime>
        <distanceMoved>0.09999937</distanceMoved>
      </movement>
    </Information>
    <Information>
      <idleTime>0</idleTime>
      <movement>
        <startPosition>
          <x>18.990612</x>
          <y>0.98</y>
          <z>18.5138588</z>
        </startPosition>
        <endPosition>
          <x>18.89088</x>
          <y>0.98</y>
          <z>18.521183</z>
        </endPosition>
        <startTime>14.2747259</startTime>
        <endTime>14.2912922</endTime>
        <totalTime>0.0165662766</totalTime>
        <distanceMoved>0.100000024</distanceMoved>
      </movement>
    </Information>
    <Information>
      <idleTime>0</idleTime>
      <movement>
        <startPosition>
          <x>18.89088</x>
          <y>0.98</y>
          <z>18.521183</z>
        </startPosition>
        <endPosition>
          <x>18.5911865</x>
          <y>0.98</y>
          <z>18.5339184</z>
        </endPosition>
        <startTime>14.2912922</startTime>
        <endTime>14.3409948</endTime>
        <totalTime>0.0497026443</totalTime>
        <distanceMoved>0.299964517</distanceMoved>
      </movement>
    </Information>
    <Information>
      <idleTime>0</idleTime>
      <movement>
        <startPosition>
          <x>18.5911865</x>
          <y>0.98</y>
          <z>18.5339184</z>
        </startPosition>
        <endPosition>
          <x>18.3914185</x>
          <y>0.98</y>
          <z>18.5246716</z>
        </endPosition>
        <startTime>14.3409948</startTime>
        <endTime>14.3906965</endTime>
        <totalTime>0.04970169</totalTime>
        <distanceMoved>0.199981958</distanceMoved>
      </movement>
    </Information>
    <Information>
      <idleTime>0</idleTime>
      <movement>
        <startPosition>
          <x>18.3914185</x>
          <y>0.98</y>
          <z>18.5246716</z>
        </startPosition>
        <endPosition>
          <x>18.2922421</x>
          <y>0.98</y>
          <z>18.511858</z>
        </endPosition>
        <startTime>14.3906965</startTime>
        <endTime>14.4072647</endTime>
        <totalTime>0.0165681839</totalTime>
        <distanceMoved>0.100000732</distanceMoved>
      </movement>
    </Information>
    <Information>
      <idleTime>0</idleTime>
      <movement>
        <startPosition>
          <x>18.2922421</x>
          <y>0.98</y>
          <z>18.511858</z>
        </startPosition>
        <endPosition>
          <x>18.2922421</x>
          <y>0.98</y>
          <z>18.511858</z>
        </endPosition>
        <startTime>14.4072647</startTime>
        <endTime>14.4072647</endTime>
        <totalTime>0</totalTime>
        <distanceMoved>0</distanceMoved>
      </movement>
    </Information>
    <Information>
      <idleTime>0</idleTime>
      <movement>
        <startPosition>
          <x>18.2922421</x>
          <y>0.98</y>
          <z>18.511858</z>
        </startPosition>
        <endPosition>
          <x>18.0047016</x>
          <y>0.98</y>
          <z>18.4295788</z>
        </endPosition>
        <startTime>14.4072647</startTime>
        <endTime>14.4735317</endTime>
        <totalTime>0.06626701</totalTime>
        <distanceMoved>0.299080878</distanceMoved>
      </movement>
    </Information>
    <Information>
      <idleTime>0</idleTime>
      <movement>
        <startPosition>
          <x>18.0047016</x>
          <y>0.98</y>
          <z>18.4295788</z>
        </startPosition>
        <endPosition>
          <x>17.8323269</x>
          <y>0.98</y>
          <z>18.3287354</z>
        </endPosition>
        <startTime>14.4735317</startTime>
        <endTime>14.5066624</endTime>
        <totalTime>0.0331306458</totalTime>
        <distanceMoved>0.1997059</distanceMoved>
      </movement>
    </Information>
    <Information>
      <idleTime>0</idleTime>
      <movement>
        <startPosition>
          <x>17.8323269</x>
          <y>0.98</y>
          <z>18.3287354</z>
        </startPosition>
        <endPosition>
          <x>17.7537327</x>
          <y>0.98</y>
          <z>18.2669048</z>
        </endPosition>
        <startTime>14.5066624</startTime>
        <endTime>14.5397921</endTime>
        <totalTime>0.0331296921</totalTime>
        <distanceMoved>0.100000314</distanceMoved>
      </movement>
    </Information>
    <Information>
      <idleTime>0</idleTime>
      <movement>
        <startPosition>
          <x>17.7537327</x>
          <y>0.98</y>
          <z>18.2669048</z>
        </startPosition>
        <endPosition>
          <x>17.7537327</x>
          <y>0.98</y>
          <z>18.2669048</z>
        </endPosition>
        <startTime>14.5397921</startTime>
        <endTime>14.5397921</endTime>
        <totalTime>0</totalTime>
        <distanceMoved>0</distanceMoved>
      </movement>
    </Information>
    <Information>
      <idleTime>0.231936455</idleTime>
      <movement>
        <startPosition>
          <x>16.6845856</x>
          <y>0.98</y>
          <z>17.7909451</z>
        </startPosition>
        <endPosition>
          <x>16.7476921</x>
          <y>0.98</y>
          <z>17.4977818</z>
        </endPosition>
        <startTime>14.7717285</startTime>
        <endTime>14.8379946</endTime>
        <totalTime>0.06626606</totalTime>
        <distanceMoved>0.299878567</distanceMoved>
      </movement>
    </Information>
    <Information>
      <idleTime>0</idleTime>
      <movement>
        <startPosition>
          <x>16.7476921</x>
          <y>0.98</y>
          <z>17.4977818</z>
        </startPosition>
        <endPosition>
          <x>16.7706966</x>
          <y>0.98</y>
          <z>17.4004631</z>
        </endPosition>
        <startTime>14.8379946</startTime>
        <endTime>14.8545589</endTime>
        <totalTime>0.01656437</totalTime>
        <distanceMoved>0.100000642</distanceMoved>
      </movement>
    </Information>
    <Information>
      <idleTime>0</idleTime>
      <movement>
        <startPosition>
          <x>16.7706966</x>
          <y>0.98</y>
          <z>17.4004631</z>
        </startPosition>
        <endPosition>
          <x>16.7937031</x>
          <y>0.98</y>
          <z>17.3031464</z>
        </endPosition>
        <startTime>14.8545589</startTime>
        <endTime>14.8711252</endTime>
        <totalTime>0.0165662766</totalTime>
        <distanceMoved>0.09999922</distanceMoved>
      </movement>
    </Information>
    <Information>
      <idleTime>0</idleTime>
      <movement>
        <startPosition>
          <x>16.7937031</x>
          <y>0.98</y>
          <z>17.3031464</z>
        </startPosition>
        <endPosition>
          <x>16.8167076</x>
          <y>0.98</y>
          <z>17.2058277</z>
        </endPosition>
        <startTime>14.8711252</startTime>
        <endTime>14.8876925</endTime>
        <totalTime>0.01656723</totalTime>
        <distanceMoved>0.100000642</distanceMoved>
      </movement>
    </Information>
    <Information>
      <idleTime>0</idleTime>
      <movement>
        <startPosition>
          <x>16.8167076</x>
          <y>0.98</y>
          <z>17.2058277</z>
        </startPosition>
        <endPosition>
          <x>16.8398819</x>
          <y>0.98</y>
          <z>17.10855</z>
        </endPosition>
        <startTime>14.8876925</startTime>
        <endTime>14.9042616</endTime>
        <totalTime>0.0165691376</totalTime>
        <distanceMoved>0.100000866</distanceMoved>
      </movement>
    </Information>
    <Information>
      <idleTime>0</idleTime>
      <movement>
        <startPosition>
          <x>16.8398819</x>
          <y>0.98</y>
          <z>17.10855</z>
        </startPosition>
        <endPosition>
          <x>16.8633957</x>
          <y>0.98</y>
          <z>17.0113544</z>
        </endPosition>
        <startTime>14.9042616</startTime>
        <endTime>14.9373922</endTime>
        <totalTime>0.0331306458</totalTime>
        <distanceMoved>0.09999851</distanceMoved>
      </movement>
    </Information>
    <Information>
      <idleTime>0</idleTime>
      <movement>
        <startPosition>
          <x>16.8633957</x>
          <y>0.98</y>
          <z>17.0113544</z>
        </startPosition>
        <endPosition>
          <x>16.887249</x>
          <y>0.98</y>
          <z>16.91424</z>
        </endPosition>
        <startTime>14.9373922</startTime>
        <endTime>14.9539585</endTime>
        <totalTime>0.0165662766</totalTime>
        <distanceMoved>0.1000011</distanceMoved>
      </movement>
    </Information>
    <Information>
      <idleTime>0</idleTime>
      <movement>
        <startPosition>
          <x>16.887249</x>
          <y>0.98</y>
          <z>16.91424</z>
        </startPosition>
        <endPosition>
          <x>16.911272</x>
          <y>0.98</y>
          <z>16.81717</z>
        </endPosition>
        <startTime>14.9539585</startTime>
        <endTime>14.9705257</endTime>
        <totalTime>0.01656723</totalTime>
        <distanceMoved>0.09999913</distanceMoved>
      </movement>
    </Information>
    <Information>
      <idleTime>0</idleTime>
      <movement>
        <startPosition>
          <x>16.911272</x>
          <y>0.98</y>
          <z>16.81717</z>
        </startPosition>
        <endPosition>
          <x>17.46075</x>
          <y>0.98</y>
          <z>13.7719145</z>
        </endPosition>
        <startTime>14.9705257</startTime>
        <endTime>15.5834923</endTime>
        <totalTime>0.612966537</totalTime>
        <distanceMoved>3.094431</distanceMoved>
      </movement>
    </Information>
    <Information>
      <idleTime>0</idleTime>
      <movement>
        <startPosition>
          <x>17.46075</x>
          <y>0.98</y>
          <z>13.7719145</z>
        </startPosition>
        <endPosition>
          <x>17.4743233</x>
          <y>0.98</y>
          <z>13.67284</z>
        </endPosition>
        <startTime>15.5834923</startTime>
        <endTime>15.6000586</endTime>
        <totalTime>0.0165662766</totalTime>
        <distanceMoved>0.09999974</distanceMoved>
      </movement>
    </Information>
    <Information>
      <idleTime>0</idleTime>
      <movement>
        <startPosition>
          <x>17.4743233</x>
          <y>0.98</y>
          <z>13.67284</z>
        </startPosition>
        <endPosition>
          <x>17.7342262</x>
          <y>0.98</y>
          <z>11.5890293</z>
        </endPosition>
        <startTime>15.6000586</startTime>
        <endTime>16.0308323</endTime>
        <totalTime>0.430773735</totalTime>
        <distanceMoved>2.09995651</distanceMoved>
      </movement>
    </Information>
    <Information>
      <idleTime>0</idleTime>
      <movement>
        <startPosition>
          <x>17.7342262</x>
          <y>0.98</y>
          <z>11.5890293</z>
        </startPosition>
        <endPosition>
          <x>17.77736</x>
          <y>0.98</y>
          <z>11.2921467</z>
        </endPosition>
        <startTime>16.0308323</startTime>
        <endTime>16.08049</endTime>
        <totalTime>0.04965782</totalTime>
        <distanceMoved>0.299999833</distanceMoved>
      </movement>
    </Information>
    <Information>
      <idleTime>0</idleTime>
      <movement>
        <startPosition>
          <x>17.77736</x>
          <y>0.98</y>
          <z>11.2921467</z>
        </startPosition>
        <endPosition>
          <x>17.77736</x>
          <y>0.98</y>
          <z>11.2921467</z>
        </endPosition>
        <startTime>16.08049</startTime>
        <endTime>16.09706</endTime>
        <totalTime>0.0165691376</totalTime>
        <distanceMoved>0</distanceMoved>
      </movement>
    </Information>
    <Information>
      <idleTime>0</idleTime>
      <movement>
        <startPosition>
          <x>17.77736</x>
          <y>0.98</y>
          <z>11.2921467</z>
        </startPosition>
        <endPosition>
          <x>17.79145</x>
          <y>0.98</y>
          <z>11.1931438</z>
        </endPosition>
        <startTime>16.09706</startTime>
        <endTime>16.1136265</endTime>
        <totalTime>0.01656723</totalTime>
        <distanceMoved>0.100000389</distanceMoved>
      </movement>
    </Information>
    <Information>
      <idleTime>0</idleTime>
      <movement>
        <startPosition>
          <x>17.79145</x>
          <y>0.98</y>
          <z>11.1931438</z>
        </startPosition>
        <endPosition>
          <x>17.8619022</x>
          <y>0.98</y>
          <z>10.6981325</z>
        </endPosition>
        <startTime>16.1136265</startTime>
        <endTime>16.2130241</endTime>
        <totalTime>0.09939766</totalTime>
        <distanceMoved>0.499999642</distanceMoved>
      </movement>
    </Information>
    <Information>
      <idleTime>0</idleTime>
      <movement>
        <startPosition>
          <x>17.8619022</x>
          <y>0.98</y>
          <z>10.6981325</z>
        </startPosition>
        <endPosition>
          <x>17.8759918</x>
          <y>0.98</y>
          <z>10.59913</z>
        </endPosition>
        <startTime>16.2130241</startTime>
        <endTime>16.2295933</endTime>
        <totalTime>0.0165691376</totalTime>
        <distanceMoved>0.100000389</distanceMoved>
      </movement>
    </Information>
    <Information>
      <idleTime>0</idleTime>
      <movement>
        <startPosition>
          <x>17.8759918</x>
          <y>0.98</y>
          <z>10.59913</z>
        </startPosition>
        <endPosition>
          <x>18.0450745</x>
          <y>0.98</y>
          <z>9.411107</z>
        </endPosition>
        <startTime>16.2295933</startTime>
        <endTime>16.4628563</endTime>
        <totalTime>0.233263016</totalTime>
        <distanceMoved>1.19999444</distanceMoved>
      </movement>
    </Information>
    <Information>
      <idleTime>0.8117752</idleTime>
      <movement>
        <startPosition>
          <x>17.8973637</x>
          <y>0.980000138</y>
          <z>7.87394428</z>
        </startPosition>
        <endPosition>
          <x>18.03278</x>
          <y>0.98</y>
          <z>6.322623</z>
        </endPosition>
        <startTime>17.2746315</startTime>
        <endTime>17.5893936</endTime>
        <totalTime>0.314762115</totalTime>
        <distanceMoved>1.55722058</distanceMoved>
      </movement>
    </Information>
    <Information>
      <idleTime>0</idleTime>
      <movement>
        <startPosition>
          <x>18.03278</x>
          <y>0.98</y>
          <z>6.322623</z>
        </startPosition>
        <endPosition>
          <x>18.0104866</x>
          <y>0.98</y>
          <z>6.12387037</z>
        </endPosition>
        <startTime>17.5893936</startTime>
        <endTime>17.6390915</endTime>
        <totalTime>0.049697876</totalTime>
        <distanceMoved>0.199998751</distanceMoved>
      </movement>
    </Information>
    <Information>
      <idleTime>0</idleTime>
      <movement>
        <startPosition>
          <x>18.0104866</x>
          <y>0.98</y>
          <z>6.12387037</z>
        </startPosition>
        <endPosition>
          <x>18.0024662</x>
          <y>0.98</y>
          <z>6.02419233</z>
        </endPosition>
        <startTime>17.6390915</startTime>
        <endTime>17.6556587</endTime>
        <totalTime>0.01656723</totalTime>
        <distanceMoved>0.100000188</distanceMoved>
      </movement>
    </Information>
    <Information>
      <idleTime>0</idleTime>
      <movement>
        <startPosition>
          <x>18.0024662</x>
          <y>0.98</y>
          <z>6.02419233</z>
        </startPosition>
        <endPosition>
          <x>17.9960136</x>
          <y>0.98</y>
          <z>5.924401</z>
        </endPosition>
        <startTime>17.6556587</startTime>
        <endTime>17.6722279</endTime>
        <totalTime>0.0165691376</totalTime>
        <distanceMoved>0.09999992</distanceMoved>
      </movement>
    </Information>
    <Information>
      <idleTime>0</idleTime>
      <movement>
        <startPosition>
          <x>17.9960136</x>
          <y>0.98</y>
          <z>5.924401</z>
        </startPosition>
        <endPosition>
          <x>17.9906063</x>
          <y>0.98</y>
          <z>5.82454729</z>
        </endPosition>
        <startTime>17.6722279</startTime>
        <endTime>17.6887913</endTime>
        <totalTime>0.0165634155</totalTime>
        <distanceMoved>0.0999998152</distanceMoved>
      </movement>
    </Information>
    <Information>
      <idleTime>0</idleTime>
      <movement>
        <startPosition>
          <x>17.9906063</x>
          <y>0.98</y>
          <z>5.82454729</z>
        </startPosition>
        <endPosition>
          <x>17.984499</x>
          <y>0.98</y>
          <z>5.62464952</z>
        </endPosition>
        <startTime>17.6887913</startTime>
        <endTime>17.7219315</endTime>
        <totalTime>0.0331401825</totalTime>
        <distanceMoved>0.199991032</distanceMoved>
      </movement>
    </Information>
    <Information>
      <idleTime>0</idleTime>
      <movement>
        <startPosition>
          <x>17.984499</x>
          <y>0.98</y>
          <z>5.62464952</z>
        </startPosition>
        <endPosition>
          <x>18.0240345</x>
          <y>0.98</y>
          <z>5.22679234</z>
        </endPosition>
        <startTime>17.7219315</startTime>
        <endTime>17.8047829</endTime>
        <totalTime>0.08285141</totalTime>
        <distanceMoved>0.3998167</distanceMoved>
      </movement>
    </Information>
    <Information>
      <idleTime>0</idleTime>
      <movement>
        <startPosition>
          <x>18.0240345</x>
          <y>0.98</y>
          <z>5.22679234</z>
        </startPosition>
        <endPosition>
          <x>18.0412273</x>
          <y>0.98</y>
          <z>5.12828159</z>
        </endPosition>
        <startTime>17.8047829</startTime>
        <endTime>17.8213253</endTime>
        <totalTime>0.0165424347</totalTime>
        <distanceMoved>0.0999998</distanceMoved>
      </movement>
    </Information>
    <Information>
      <idleTime>0</idleTime>
      <movement>
        <startPosition>
          <x>18.0412273</x>
          <y>0.98</y>
          <z>5.12828159</z>
        </startPosition>
        <endPosition>
          <x>18.124115</x>
          <y>0.98</y>
          <z>4.84047174</z>
        </endPosition>
        <startTime>17.8213253</startTime>
        <endTime>17.8875923</endTime>
        <totalTime>0.06626701</totalTime>
        <distanceMoved>0.2995077</distanceMoved>
      </movement>
    </Information>
    <Information>
      <idleTime>0</idleTime>
      <movement>
        <startPosition>
          <x>18.124115</x>
          <y>0.98</y>
          <z>4.84047174</z>
        </startPosition>
        <endPosition>
          <x>18.1688919</x>
          <y>0.980000138</y>
          <z>4.75105667</z>
        </endPosition>
        <startTime>17.8875923</startTime>
        <endTime>17.9041576</endTime>
        <totalTime>0.0165653229</totalTime>
        <distanceMoved>0.100000136</distanceMoved>
      </movement>
    </Information>
    <Information>
      <idleTime>0.06626701</idleTime>
      <movement>
        <startPosition>
          <x>18.34536</x>
          <y>0.980000138</y>
          <z>4.50960541</z>
        </startPosition>
        <endPosition>
          <x>18.4216957</x>
          <y>0.9800001</y>
          <z>4.44500971</z>
        </endPosition>
        <startTime>17.9704247</startTime>
        <endTime>17.9869938</endTime>
        <totalTime>0.0165691376</totalTime>
        <distanceMoved>0.09999888</distanceMoved>
      </movement>
    </Information>
    <Information>
      <idleTime>0</idleTime>
      <movement>
        <startPosition>
          <x>18.4216957</x>
          <y>0.9800001</y>
          <z>4.44500971</z>
        </startPosition>
        <endPosition>
          <x>18.5044823</x>
          <y>0.98</y>
          <z>4.38891554</z>
        </endPosition>
        <startTime>17.9869938</startTime>
        <endTime>18.00356</endTime>
        <totalTime>0.0165653229</totalTime>
        <distanceMoved>0.100000851</distanceMoved>
      </movement>
    </Information>
    <Information>
      <idleTime>0</idleTime>
      <movement>
        <startPosition>
          <x>18.5044823</x>
          <y>0.98</y>
          <z>4.38891554</z>
        </startPosition>
        <endPosition>
          <x>18.5946369</x>
          <y>0.980000138</y>
          <z>4.34564972</z>
        </endPosition>
        <startTime>18.00356</startTime>
        <endTime>18.0201244</endTime>
        <totalTime>0.0165653229</totalTime>
        <distanceMoved>0.09999896</distanceMoved>
      </movement>
    </Information>
    <Information>
      <idleTime>0</idleTime>
      <movement>
        <startPosition>
          <x>18.5946369</x>
          <y>0.980000138</y>
          <z>4.34564972</z>
        </startPosition>
        <endPosition>
          <x>18.5946369</x>
          <y>0.980000138</y>
          <z>4.34564972</z>
        </endPosition>
        <startTime>18.0201244</startTime>
        <endTime>18.0366917</endTime>
        <totalTime>0.01656723</totalTime>
        <distanceMoved>0</distanceMoved>
      </movement>
    </Information>
    <Information>
      <idleTime>0</idleTime>
      <movement>
        <startPosition>
          <x>18.5946369</x>
          <y>0.980000138</y>
          <z>4.34564972</z>
        </startPosition>
        <endPosition>
          <x>18.99001</x>
          <y>0.98</y>
          <z>4.354664</z>
        </endPosition>
        <startTime>18.0366917</startTime>
        <endTime>18.1029625</endTime>
        <totalTime>0.06627083</totalTime>
        <distanceMoved>0.395475119</distanceMoved>
      </movement>
    </Information>
    <Information>
      <idleTime>0</idleTime>
      <movement>
        <startPosition>
          <x>18.99001</x>
          <y>0.98</y>
          <z>4.354664</z>
        </startPosition>
        <endPosition>
          <x>19.3687267</x>
          <y>0.98</y>
          <z>4.6731925</z>
        </endPosition>
        <startTime>18.1029625</startTime>
        <endTime>18.2023582</endTime>
        <totalTime>0.09939575</totalTime>
        <distanceMoved>0.494860977</distanceMoved>
      </movement>
    </Information>
    <Information>
      <idleTime>0</idleTime>
      <movement>
        <startPosition>
          <x>19.3687267</x>
          <y>0.98</y>
          <z>4.6731925</z>
        </startPosition>
        <endPosition>
          <x>19.6260262</x>
          <y>0.98</y>
          <z>5.21220541</z>
        </endPosition>
        <startTime>18.2023582</startTime>
        <endTime>18.33489</endTime>
        <totalTime>0.13253212</totalTime>
        <distanceMoved>0.597275436</distanceMoved>
      </movement>
    </Information>
    <Information>
      <idleTime>0</idleTime>
      <movement>
        <startPosition>
          <x>19.6260262</x>
          <y>0.98</y>
          <z>5.21220541</z>
        </startPosition>
        <endPosition>
          <x>19.65275</x>
          <y>0.98</y>
          <z>5.30856848</z>
        </endPosition>
        <startTime>18.33489</startTime>
        <endTime>18.3514576</endTime>
        <totalTime>0.01656723</totalTime>
        <distanceMoved>0.100000024</distanceMoved>
      </movement>
    </Information>
    <Information>
      <idleTime>0</idleTime>
      <movement>
        <startPosition>
          <x>19.65275</x>
          <y>0.98</y>
          <z>5.30856848</z>
        </startPosition>
        <endPosition>
          <x>19.65275</x>
          <y>0.98</y>
          <z>5.30856848</z>
        </endPosition>
        <startTime>18.3514576</startTime>
        <endTime>18.3514576</endTime>
        <totalTime>0</totalTime>
        <distanceMoved>0</distanceMoved>
      </movement>
    </Information>
    <Information>
      <idleTime>0.977432251</idleTime>
      <movement>
        <startPosition>
          <x>18.9691563</x>
          <y>0.980000138</y>
          <z>6.416118</z>
        </startPosition>
        <endPosition>
          <x>19.4564743</x>
          <y>0.98</y>
          <z>5.78189373</z>
        </endPosition>
        <startTime>19.32889</startTime>
        <endTime>19.4945641</endTime>
        <totalTime>0.16567421</totalTime>
        <distanceMoved>0.799824655</distanceMoved>
      </movement>
    </Information>
    <Information>
      <idleTime>0</idleTime>
      <movement>
        <startPosition>
          <x>19.4564743</x>
          <y>0.98</y>
          <z>5.78189373</z>
        </startPosition>
        <endPosition>
          <x>19.6927166</x>
          <y>0.980000138</y>
          <z>5.45911</z>
        </endPosition>
        <startTime>19.4945641</startTime>
        <endTime>19.5608253</endTime>
        <totalTime>0.06626129</totalTime>
        <distanceMoved>0.399999857</distanceMoved>
      </movement>
    </Information>
    <Information>
      <idleTime>0</idleTime>
      <movement>
        <startPosition>
          <x>19.6927166</x>
          <y>0.980000138</y>
          <z>5.45911</z>
        </startPosition>
        <endPosition>
          <x>19.6927166</x>
          <y>0.980000138</y>
          <z>5.45911</z>
        </endPosition>
        <startTime>19.5608253</startTime>
        <endTime>19.5773926</endTime>
        <totalTime>0.01656723</totalTime>
        <distanceMoved>0</distanceMoved>
      </movement>
    </Information>
    <Information>
      <idleTime>0</idleTime>
      <movement>
        <startPosition>
          <x>19.6927166</x>
          <y>0.980000138</y>
          <z>5.45911</z>
        </startPosition>
        <endPosition>
          <x>19.7517757</x>
          <y>0.9800001</y>
          <z>5.37841368</z>
        </endPosition>
        <startTime>19.5773926</startTime>
        <endTime>19.5939579</endTime>
        <totalTime>0.0165653229</totalTime>
        <distanceMoved>0.09999922</distanceMoved>
      </movement>
    </Information>
    <Information>
      <idleTime>0</idleTime>
      <movement>
        <startPosition>
          <x>19.7517757</x>
          <y>0.9800001</y>
          <z>5.37841368</z>
        </startPosition>
        <endPosition>
          <x>24.5356827</x>
          <y>0.9800001</y>
          <z>-1.15796483</z>
        </endPosition>
        <startTime>19.5939579</startTime>
        <endTime>20.42229</endTime>
        <totalTime>0.8283329</totalTime>
        <distanceMoved>8.1</distanceMoved>
      </movement>
    </Information>
    <Information>
      <idleTime>0</idleTime>
      <movement>
        <startPosition>
          <x>24.5356827</x>
          <y>0.9800001</y>
          <z>-1.15796483</z>
        </startPosition>
        <endPosition>
          <x>24.5356827</x>
          <y>0.9800001</y>
          <z>-1.15796483</z>
        </endPosition>
        <startTime>20.42229</startTime>
        <endTime>20.438858</endTime>
        <totalTime>0.01656723</totalTime>
        <distanceMoved>0</distanceMoved>
      </movement>
    </Information>
    <Information>
      <idleTime>0</idleTime>
      <movement>
        <startPosition>
          <x>24.5356827</x>
          <y>0.9800001</y>
          <z>-1.15796483</z>
        </startPosition>
        <endPosition>
          <x>24.6533813</x>
          <y>0.9800001</y>
          <z>-1.31966543</z>
        </endPosition>
        <startTime>20.438858</startTime>
        <endTime>20.4719925</endTime>
        <totalTime>0.03313446</totalTime>
        <distanceMoved>0.200000152</distanceMoved>
      </movement>
    </Information>
    <Information>
      <idleTime>0</idleTime>
      <movement>
        <startPosition>
          <x>24.6533813</x>
          <y>0.9800001</y>
          <z>-1.31966543</z>
        </startPosition>
        <endPosition>
          <x>24.712019</x>
          <y>0.98</y>
          <z>-1.40066969</z>
        </endPosition>
        <startTime>20.4719925</startTime>
        <endTime>20.4885578</endTime>
        <totalTime>0.0165653229</totalTime>
        <distanceMoved>0.100000307</distanceMoved>
      </movement>
    </Information>
    <Information>
      <idleTime>0</idleTime>
      <movement>
        <startPosition>
          <x>24.712019</x>
          <y>0.98</y>
          <z>-1.40066969</z>
        </startPosition>
        <endPosition>
          <x>26.6819553</x>
          <y>0.98</y>
          <z>-4.171735</z>
        </endPosition>
        <startTime>20.4885578</startTime>
        <endTime>21.1677914</endTime>
        <totalTime>0.679233551</totalTime>
        <distanceMoved>3.39991951</distanceMoved>
      </movement>
    </Information>
    <Information>
      <idleTime>0</idleTime>
      <movement>
        <startPosition>
          <x>26.6819553</x>
          <y>0.98</y>
          <z>-4.171735</z>
        </startPosition>
        <endPosition>
          <x>26.92371</x>
          <y>0.98</y>
          <z>-4.490237</z>
        </endPosition>
        <startTime>21.1677914</startTime>
        <endTime>21.2538033</endTime>
        <totalTime>0.08601189</totalTime>
        <distanceMoved>0.399861276</distanceMoved>
      </movement>
    </Information>
    <Information>
      <idleTime>0</idleTime>
      <movement>
        <startPosition>
          <x>26.92371</x>
          <y>0.98</y>
          <z>-4.490237</z>
        </startPosition>
        <endPosition>
          <x>27.5024757</x>
          <y>0.9800001</y>
          <z>-5.179439</z>
        </endPosition>
        <startTime>21.2538033</startTime>
        <endTime>21.4328613</endTime>
        <totalTime>0.179058075</totalTime>
        <distanceMoved>0.8999828</distanceMoved>
      </movement>
    </Information>
    <Information>
      <idleTime>0</idleTime>
      <movement>
        <startPosition>
          <x>27.5024757</x>
          <y>0.9800001</y>
          <z>-5.179439</z>
        </startPosition>
        <endPosition>
          <x>27.5675526</x>
          <y>0.98</y>
          <z>-5.25536633</z>
        </endPosition>
        <startTime>21.4328613</startTime>
        <endTime>21.4494247</endTime>
        <totalTime>0.0165634155</totalTime>
        <distanceMoved>0.09999971</distanceMoved>
      </movement>
    </Information>
    <Information>
      <idleTime>0</idleTime>
      <movement>
        <startPosition>
          <x>27.5675526</x>
          <y>0.98</y>
          <z>-5.25536633</z>
        </startPosition>
        <endPosition>
          <x>31.2585258</x>
          <y>0.9800001</y>
          <z>-9.729307</z>
        </endPosition>
        <startTime>21.4494247</startTime>
        <endTime>22.6090946</endTime>
        <totalTime>1.15966988</totalTime>
        <distanceMoved>5.799951</distanceMoved>
      </movement>
    </Information>
    <Information>
      <idleTime>2.435297</idleTime>
      <movement>
        <startPosition>
          <x>32.32447</x>
          <y>0.98</y>
          <z>-11.0528173</z>
        </startPosition>
        <endPosition>
          <x>32.5180626</x>
          <y>0.98</y>
          <z>-11.4027805</z>
        </endPosition>
        <startTime>25.0443916</startTime>
        <endTime>25.1272259</endTime>
        <totalTime>0.0828342438</totalTime>
        <distanceMoved>0.399940133</distanceMoved>
      </movement>
    </Information>
    <Information>
      <idleTime>0</idleTime>
      <movement>
        <startPosition>
          <x>32.5180626</x>
          <y>0.98</y>
          <z>-11.4027805</z>
        </startPosition>
        <endPosition>
          <x>32.5648537</x>
          <y>0.98</y>
          <z>-11.4911566</z>
        </endPosition>
        <startTime>25.1272259</startTime>
        <endTime>25.1437931</endTime>
        <totalTime>0.01656723</totalTime>
        <distanceMoved>0.09999865</distanceMoved>
      </movement>
    </Information>
    <Information>
      <idleTime>0</idleTime>
      <movement>
        <startPosition>
          <x>32.5648537</x>
          <y>0.98</y>
          <z>-11.4911566</z>
        </startPosition>
        <endPosition>
          <x>32.65689</x>
          <y>0.98</y>
          <z>-11.6687174</z>
        </endPosition>
        <startTime>25.1437931</startTime>
        <endTime>25.193491</endTime>
        <totalTime>0.049697876</totalTime>
        <distanceMoved>0.199996725</distanceMoved>
      </movement>
    </Information>
    <Information>
      <idleTime>0</idleTime>
      <movement>
        <startPosition>
          <x>32.65689</x>
          <y>0.98</y>
          <z>-11.6687174</z>
        </startPosition>
        <endPosition>
          <x>32.70229</x>
          <y>0.98</y>
          <z>-11.7578182</z>
        </endPosition>
        <startTime>25.193491</startTime>
        <endTime>25.2100639</endTime>
        <totalTime>0.0165729523</totalTime>
        <distanceMoved>0.100000016</distanceMoved>
      </movement>
    </Information>
    <Information>
      <idleTime>0</idleTime>
      <movement>
        <startPosition>
          <x>32.70229</x>
          <y>0.98</y>
          <z>-11.7578182</z>
        </startPosition>
        <endPosition>
          <x>33.11088</x>
          <y>0.98</y>
          <z>-12.5597239</z>
        </endPosition>
        <startTime>25.2100639</startTime>
        <endTime>25.39229</endTime>
        <totalTime>0.182226181</totalTime>
        <distanceMoved>0.900000155</distanceMoved>
      </movement>
    </Information>
    <Information>
      <idleTime>0</idleTime>
      <movement>
        <startPosition>
          <x>33.11088</x>
          <y>0.98</y>
          <z>-12.5597239</z>
        </startPosition>
        <endPosition>
          <x>33.15628</x>
          <y>0.98</y>
          <z>-12.6488247</z>
        </endPosition>
        <startTime>25.39229</startTime>
        <endTime>25.4088631</endTime>
        <totalTime>0.0165729523</totalTime>
        <distanceMoved>0.100000016</distanceMoved>
      </movement>
    </Information>
    <Information>
      <idleTime>0</idleTime>
      <movement>
        <startPosition>
          <x>33.15628</x>
          <y>0.98</y>
          <z>-12.6488247</z>
        </startPosition>
        <endPosition>
          <x>33.5661736</x>
          <y>0.98</y>
          <z>-13.55955</z>
        </endPosition>
        <startTime>25.4088631</startTime>
        <endTime>25.60766</endTime>
        <totalTime>0.198797226</totalTime>
        <distanceMoved>0.9987159</distanceMoved>
      </movement>
    </Information>
    <Information>
      <idleTime>1.5406971</idleTime>
      <movement>
        <startPosition>
          <x>32.5635529</x>
          <y>0.98</y>
          <z>-14.6373892</z>
        </startPosition>
        <endPosition>
          <x>32.16683</x>
          <y>0.98</y>
          <z>-14.597971</z>
        </endPosition>
        <startTime>27.1483574</startTime>
        <endTime>27.2311916</endTime>
        <totalTime>0.0828342438</totalTime>
        <distanceMoved>0.398678154</distanceMoved>
      </movement>
    </Information>
    <Information>
      <idleTime>0</idleTime>
      <movement>
        <startPosition>
          <x>32.16683</x>
          <y>0.98</y>
          <z>-14.597971</z>
        </startPosition>
        <endPosition>
          <x>32.0669022</x>
          <y>0.98</y>
          <z>-14.60181</z>
        </endPosition>
        <startTime>27.2311916</startTime>
        <endTime>27.247757</endTime>
        <totalTime>0.0165653229</totalTime>
        <distanceMoved>0.0999997258</distanceMoved>
      </movement>
    </Information>
    <Information>
      <idleTime>0</idleTime>
      <movement>
        <startPosition>
          <x>32.0669022</x>
          <y>0.98</y>
          <z>-14.60181</z>
        </startPosition>
        <endPosition>
          <x>29.96885</x>
          <y>0.98</y>
          <z>-14.6920156</z>
        </endPosition>
        <startTime>27.247757</startTime>
        <endTime>27.67849</endTime>
        <totalTime>0.430732727</totalTime>
        <distanceMoved>2.09999132</distanceMoved>
      </movement>
    </Information>
    <Information>
      <idleTime>0</idleTime>
      <movement>
        <startPosition>
          <x>29.96885</x>
          <y>0.98</y>
          <z>-14.6920156</z>
        </startPosition>
        <endPosition>
          <x>29.8690567</x>
          <y>0.98</y>
          <z>-14.6984692</z>
        </endPosition>
        <startTime>27.67849</startTime>
        <endTime>27.6950626</endTime>
        <totalTime>0.0165729523</totalTime>
        <distanceMoved>0.100000933</distanceMoved>
      </movement>
    </Information>
    <Information>
      <idleTime>0</idleTime>
      <movement>
        <startPosition>
          <x>29.8690567</x>
          <y>0.98</y>
          <z>-14.6984692</z>
        </startPosition>
        <endPosition>
          <x>29.7693</x>
          <y>0.98</y>
          <z>-14.7054453</z>
        </endPosition>
        <startTime>27.6950626</startTime>
        <endTime>27.7116241</endTime>
        <totalTime>0.0165615082</totalTime>
        <distanceMoved>0.09999987</distanceMoved>
      </movement>
    </Information>
    <Information>
      <idleTime>0</idleTime>
      <movement>
        <startPosition>
          <x>29.7693</x>
          <y>0.98</y>
          <z>-14.7054453</z>
        </startPosition>
        <endPosition>
          <x>29.5700321</x>
          <y>0.98</y>
          <z>-14.7225285</z>
        </endPosition>
        <startTime>27.7116241</startTime>
        <endTime>27.7449837</endTime>
        <totalTime>0.0333595276</totalTime>
        <distanceMoved>0.199999258</distanceMoved>
      </movement>
    </Information>
    <Information>
      <idleTime>0</idleTime>
      <movement>
        <startPosition>
          <x>29.5700321</x>
          <y>0.98</y>
          <z>-14.7225285</z>
        </startPosition>
        <endPosition>
          <x>28.9725819</x>
          <y>0.98</y>
          <z>-14.7777767</z>
        </endPosition>
        <startTime>27.7449837</startTime>
        <endTime>27.87729</endTime>
        <totalTime>0.132307053</totalTime>
        <distanceMoved>0.5999993</distanceMoved>
      </movement>
    </Information>
    <Information>
      <idleTime>0</idleTime>
      <movement>
        <startPosition>
          <x>28.9725819</x>
          <y>0.98</y>
          <z>-14.7777767</z>
        </startPosition>
        <endPosition>
          <x>28.8730087</x>
          <y>0.98</y>
          <z>-14.787014</z>
        </endPosition>
        <startTime>27.87729</startTime>
        <endTime>27.89386</endTime>
        <totalTime>0.0165691376</totalTime>
        <distanceMoved>0.100000687</distanceMoved>
      </movement>
    </Information>
    <Information>
      <idleTime>0</idleTime>
      <movement>
        <startPosition>
          <x>28.8730087</x>
          <y>0.98</y>
          <z>-14.787014</z>
        </startPosition>
        <endPosition>
          <x>12.8013048</x>
          <y>0.9800001</y>
          <z>-15.604413</z>
        </endPosition>
        <startTime>27.89386</startTime>
        <endTime>31.1077919</endTime>
        <totalTime>3.213932</totalTime>
        <distanceMoved>16.0924778</distanceMoved>
      </movement>
    </Information>
    <Information>
      <idleTime>0</idleTime>
      <movement>
        <startPosition>
          <x>12.8013048</x>
          <y>0.9800001</y>
          <z>-15.604413</z>
        </startPosition>
        <endPosition>
          <x>12.0346823</x>
          <y>0.9800001</y>
          <z>-15.3943739</z>
        </endPosition>
        <startTime>31.1077919</startTime>
        <endTime>31.27346</endTime>
        <totalTime>0.165668488</totalTime>
        <distanceMoved>0.7948752</distanceMoved>
      </movement>
    </Information>
    <Information>
      <idleTime>0</idleTime>
      <movement>
        <startPosition>
          <x>12.0346823</x>
          <y>0.9800001</y>
          <z>-15.3943739</z>
        </startPosition>
        <endPosition>
          <x>6.85303259</x>
          <y>0.9800001</y>
          <z>-15.3735771</z>
        </endPosition>
        <startTime>31.27346</startTime>
        <endTime>32.3171577</endTime>
        <totalTime>1.04369736</totalTime>
        <distanceMoved>5.18169165</distanceMoved>
      </movement>
    </Information>
    <Information>
      <idleTime>1.64012146</idleTime>
      <movement>
        <startPosition>
          <x>5.25351</x>
          <y>0.9800001</y>
          <z>-15.4126692</z>
        </startPosition>
        <endPosition>
          <x>4.454002</x>
          <y>0.9800001</y>
          <z>-15.4222555</z>
        </endPosition>
        <startTime>33.95728</startTime>
        <endTime>34.10638</endTime>
        <totalTime>0.149101257</totalTime>
        <distanceMoved>0.799565554</distanceMoved>
      </movement>
    </Information>
    <Information>
      <idleTime>0</idleTime>
      <movement>
        <startPosition>
          <x>4.454002</x>
          <y>0.9800001</y>
          <z>-15.4222555</z>
        </startPosition>
        <endPosition>
          <x>3.62069583</x>
          <y>0.9800001</y>
          <z>-15.0957909</z>
        </endPosition>
        <startTime>34.10638</startTime>
        <endTime>34.28</endTime>
        <totalTime>0.173618317</totalTime>
        <distanceMoved>0.8949739</distanceMoved>
      </movement>
    </Information>
  </MovementData>
  <LookData>
    <Information>
      <totalTimeFacingDirection>0.507822931</totalTimeFacingDirection>
      <tracks>
        <startTime>0</startTime>
        <forwardDirection>
          <x>0</x>
          <y>0</y>
          <z>-1</z>
        </forwardDirection>
        <ObjectDirectlyAhead>
          <name>Wall (1)</name>
          <position>
            <x>17.74287</x>
            <y>2.027443</y>
            <z>-19.74769</z>
          </position>
          <focusPoint>
            <x>19.1</x>
            <y>1.8</y>
            <z>-19.24769</z>
          </focusPoint>
        </ObjectDirectlyAhead>
      </tracks>
    </Information>
    <Information>
      <totalTimeFacingDirection>0.51357</totalTimeFacingDirection>
      <tracks>
        <startTime>0.507822931</startTime>
        <forwardDirection>
          <x>0</x>
          <y>0</y>
          <z>-1</z>
        </forwardDirection>
        <ObjectDirectlyAhead>
          <name>Wall (1)</name>
          <position>
            <x>17.74287</x>
            <y>2.027443</y>
            <z>-19.74769</z>
          </position>
          <focusPoint>
            <x>19.1</x>
            <y>1.78000009</y>
            <z>-19.24769</z>
          </focusPoint>
        </ObjectDirectlyAhead>
      </tracks>
    </Information>
    <Information>
      <totalTimeFacingDirection>0.513566</totalTimeFacingDirection>
      <tracks>
        <startTime>1.021393</startTime>
        <forwardDirection>
          <x>0.006975137</x>
          <y>-0.0418756567</y>
          <z>-0.999098659</z>
        </forwardDirection>
        <ObjectDirectlyAhead>
          <name>triggerLuzV</name>
          <position>
            <x>17.9</x>
            <y>0.3199978</y>
            <z>8.74</z>
          </position>
          <focusPoint>
            <x>19.1629848</x>
            <y>1.40187347</y>
            <z>8.978391</z>
          </focusPoint>
        </ObjectDirectlyAhead>
      </tracks>
    </Information>
    <Information>
      <totalTimeFacingDirection>1.59039986</totalTimeFacingDirection>
      <tracks>
        <startTime>1.534959</startTime>
        <forwardDirection>
          <x>0.09568683</x>
          <y>-0.05756402</y>
          <z>-0.9937457</z>
        </forwardDirection>
        <ObjectDirectlyAhead>
          <name>Floor</name>
          <position>
            <x>0</x>
            <y>0</y>
            <z>0</z>
          </position>
          <focusPoint>
            <x>21.96249</x>
            <y>2.83718238E-16</y>
            <z>-12.7775335</z>
          </focusPoint>
        </ObjectDirectlyAhead>
      </tracks>
    </Information>
    <Information>
      <totalTimeFacingDirection>0.513567448</totalTimeFacingDirection>
      <tracks>
        <startTime>3.12535882</startTime>
        <forwardDirection>
          <x>0.197421372</x>
          <y>-0.04884977</y>
          <z>-0.979100943</z>
        </forwardDirection>
        <ObjectDirectlyAhead>
          <name>triggerLuzV</name>
          <position>
            <x>17.9</x>
            <y>0.3199978</y>
            <z>8.74</z>
          </position>
          <focusPoint>
            <x>17.6968517</x>
            <y>1.39562953</y>
            <z>10.0144215</z>
          </focusPoint>
        </ObjectDirectlyAhead>
      </tracks>
    </Information>
    <Information>
      <totalTimeFacingDirection>0.51356864</totalTimeFacingDirection>
      <tracks>
        <startTime>3.63892627</startTime>
        <forwardDirection>
          <x>0.2636417</x>
          <y>-0.041875653</y>
          <z>-0.9637117</z>
        </forwardDirection>
        <ObjectDirectlyAhead>
          <name>triggerLuzV</name>
          <position>
            <x>17.9</x>
            <y>0.3199978</y>
            <z>8.74</z>
          </position>
          <focusPoint>
            <x>18.2731686</x>
            <y>1.44165087</y>
            <z>9.933749</z>
          </focusPoint>
        </ObjectDirectlyAhead>
      </tracks>
    </Information>
    <Information>
      <totalTimeFacingDirection>0.7289305</totalTimeFacingDirection>
      <tracks>
        <startTime>4.152495</startTime>
        <forwardDirection>
          <x>0.273718983</x>
          <y>-0.041875653</y>
          <z>-0.9608979</z>
        </forwardDirection>
        <ObjectDirectlyAhead>
          <name>triggerLuzV</name>
          <position>
            <x>17.9</x>
            <y>0.3199978</y>
            <z>8.74</z>
          </position>
          <focusPoint>
            <x>18.370327</x>
            <y>1.43923056</y>
            <z>9.901253</z>
          </focusPoint>
        </ObjectDirectlyAhead>
      </tracks>
    </Information>
    <Information>
      <totalTimeFacingDirection>0.5135665</totalTimeFacingDirection>
      <tracks>
        <startTime>4.88142538</startTime>
        <forwardDirection>
          <x>0.271999955</x>
          <y>-0.04536298</y>
          <z>-0.9612272</z>
        </forwardDirection>
        <ObjectDirectlyAhead>
          <name>triggerLuzV</name>
          <position>
            <x>17.9</x>
            <y>0.3199978</y>
            <z>8.74</z>
          </position>
          <focusPoint>
            <x>18.3458138</x>
            <y>1.41260958</y>
            <z>9.935766</z>
          </focusPoint>
        </ObjectDirectlyAhead>
      </tracks>
    </Information>
    <Information>
      <totalTimeFacingDirection>5.51670074</totalTimeFacingDirection>
      <tracks>
        <startTime>5.394992</startTime>
        <forwardDirection>
          <x>0.1490946</x>
          <y>-0.07671902</y>
          <z>-0.9858422</z>
        </forwardDirection>
        <ObjectDirectlyAhead>
          <name>triggerLuzV</name>
          <position>
            <x>17.9</x>
            <y>0.3199978</y>
            <z>8.74</z>
          </position>
          <focusPoint>
            <x>17.3029842</x>
            <y>1.18347907</y>
            <z>10.0516272</z>
          </focusPoint>
        </ObjectDirectlyAhead>
      </tracks>
    </Information>
    <Information>
      <totalTimeFacingDirection>0.513567</totalTimeFacingDirection>
      <tracks>
        <startTime>10.9116926</startTime>
        <forwardDirection>
          <x>0.232166544</x>
          <y>-0.104528472</y>
          <z>-0.9670435</z>
        </forwardDirection>
        <ObjectDirectlyAhead>
          <name>triggerLuzV</name>
          <position>
            <x>17.9</x>
            <y>0.3199978</y>
            <z>8.74</z>
          </position>
          <focusPoint>
            <x>17.927803</x>
            <y>0.9765258</y>
            <z>10.28615</z>
          </focusPoint>
        </ObjectDirectlyAhead>
      </tracks>
    </Information>
    <Information>
      <totalTimeFacingDirection>0.513566</totalTimeFacingDirection>
      <tracks>
        <startTime>11.42526</startTime>
        <forwardDirection>
          <x>0.0202661846</x>
          <y>-0.2520693</y>
          <z>-0.9674967</z>
        </forwardDirection>
        <ObjectDirectlyAhead>
          <name>Floor</name>
          <position>
            <x>0</x>
            <y>0</y>
            <z>0</z>
          </position>
          <focusPoint>
            <x>16.2871571</x>
            <y>-2.41607387E-16</y>
            <z>10.8810291</z>
          </focusPoint>
        </ObjectDirectlyAhead>
      </tracks>
    </Information>
    <Information>
      <totalTimeFacingDirection>0.513566</totalTimeFacingDirection>
      <tracks>
        <startTime>11.9388256</startTime>
        <forwardDirection>
          <x>0.07063821</x>
          <y>-0.435231179</y>
          <z>-0.8975432</z>
        </forwardDirection>
        <ObjectDirectlyAhead>
          <name>Floor</name>
          <position>
            <x>0</x>
            <y>0</y>
            <z>0</z>
          </position>
          <focusPoint>
            <x>16.4328556</x>
            <y>-3.11840341E-16</y>
            <z>14.0440388</z>
          </focusPoint>
        </ObjectDirectlyAhead>
      </tracks>
    </Information>
    <Information>
      <totalTimeFacingDirection>0.513566</totalTimeFacingDirection>
      <tracks>
        <startTime>12.4523916</startTime>
        <forwardDirection>
          <x>0.105778731</x>
          <y>-0.4493191</y>
          <z>-0.887086749</z>
        </forwardDirection>
        <ObjectDirectlyAhead>
          <name>FPSController</name>
          <position>
            <x>16.2310677</x>
            <y>0.98</y>
            <z>16.6187115</z>
          </position>
          <focusPoint>
            <x>16.3291149</x>
            <y>1.6733706</y>
            <z>16.51392</z>
          </focusPoint>
        </ObjectDirectlyAhead>
      </tracks>
    </Information>
    <Information>
      <totalTimeFacingDirection>0.5135689</totalTimeFacingDirection>
      <tracks>
        <startTime>12.9659576</startTime>
        <forwardDirection>
          <x>0.623660862</x>
          <y>-0.278991342</y>
          <z>-0.730213165</z>
        </forwardDirection>
        <ObjectDirectlyAhead>
          <name>Floor</name>
          <position>
            <x>0</x>
            <y>0</y>
            <z>0</z>
          </position>
          <focusPoint>
            <x>21.2068081</x>
            <y>-2.74731934E-16</y>
            <z>12.3728275</z>
          </focusPoint>
        </ObjectDirectlyAhead>
      </tracks>
    </Information>
    <Information>
      <totalTimeFacingDirection>0.513566</totalTimeFacingDirection>
      <tracks>
        <startTime>13.4795265</startTime>
        <forwardDirection>
          <x>0.472699016</x>
          <y>-0.2351424</y>
          <z>-0.8492724</z>
        </forwardDirection>
        <ObjectDirectlyAhead>
          <name>Floor</name>
          <position>
            <x>0</x>
            <y>0</y>
            <z>0</z>
          </position>
          <focusPoint>
            <x>23.0950756</x>
            <y>-2.56178524E-16</y>
            <z>11.5372543</z>
          </focusPoint>
        </ObjectDirectlyAhead>
      </tracks>
    </Information>
    <Information>
      <totalTimeFacingDirection>0.513569832</totalTimeFacingDirection>
      <tracks>
        <startTime>13.9930925</startTime>
        <forwardDirection>
          <x>-0.311342329</x>
          <y>-0.292372078</y>
          <z>-0.904204249</z>
        </forwardDirection>
        <ObjectDirectlyAhead>
          <name>Floor</name>
          <position>
            <x>0</x>
            <y>0</y>
            <z>0</z>
          </position>
          <focusPoint>
            <x>18.1514721</x>
            <y>-2.84655745E-16</y>
            <z>12.8197527</z>
          </focusPoint>
        </ObjectDirectlyAhead>
      </tracks>
    </Information>
    <Information>
      <totalTimeFacingDirection>0.513563156</totalTimeFacingDirection>
      <tracks>
        <startTime>14.5066624</startTime>
        <forwardDirection>
          <x>0.19513838</x>
          <y>-0.2990412</y>
          <z>-0.934075</z>
        </forwardDirection>
        <ObjectDirectlyAhead>
          <name>Floor</name>
          <position>
            <x>0</x>
            <y>0</y>
            <z>0</z>
          </position>
          <focusPoint>
            <x>19.01603</x>
            <y>-2.76633231E-16</y>
            <z>12.4584532</z>
          </focusPoint>
        </ObjectDirectlyAhead>
      </tracks>
    </Information>
    <Information>
      <totalTimeFacingDirection>0.513567</totalTimeFacingDirection>
      <tracks>
        <startTime>15.0202255</startTime>
        <forwardDirection>
          <x>0.24092415</x>
          <y>-0.313992947</y>
          <z>-0.918348253</z>
        </forwardDirection>
        <ObjectDirectlyAhead>
          <name>Floor</name>
          <position>
            <x>0</x>
            <y>0</y>
            <z>0</z>
          </position>
          <focusPoint>
            <x>18.479126</x>
            <y>-2.45218023E-16</y>
            <z>11.0436382</z>
          </focusPoint>
        </ObjectDirectlyAhead>
      </tracks>
    </Information>
    <Information>
      <totalTimeFacingDirection>0.513567</totalTimeFacingDirection>
      <tracks>
        <startTime>15.5337925</startTime>
        <forwardDirection>
          <x>0.1233057</x>
          <y>-0.361625075</y>
          <z>-0.9241336</z>
        </forwardDirection>
        <ObjectDirectlyAhead>
          <name>triggerLuzV</name>
          <position>
            <x>17.9</x>
            <y>0.3199978</y>
            <z>8.74</z>
          </position>
          <focusPoint>
            <x>17.85386</x>
            <y>0.451816559</y>
            <z>10.4141846</z>
          </focusPoint>
        </ObjectDirectlyAhead>
      </tracks>
    </Information>
    <Information>
      <totalTimeFacingDirection>0.514904</totalTimeFacingDirection>
      <tracks>
        <startTime>16.04736</startTime>
        <forwardDirection>
          <x>0.117814422</x>
          <y>-0.5778583</y>
          <z>-0.807589</z>
        </forwardDirection>
        <ObjectDirectlyAhead>
          <name>triggerLuzV</name>
          <position>
            <x>17.9</x>
            <y>0.3199978</y>
            <z>8.74</z>
          </position>
          <focusPoint>
            <x>17.9919147</x>
            <y>0.993436</y>
            <z>10.27637</z>
          </focusPoint>
        </ObjectDirectlyAhead>
      </tracks>
    </Information>
    <Information>
      <totalTimeFacingDirection>0.513563156</totalTimeFacingDirection>
      <tracks>
        <startTime>16.5622635</startTime>
        <forwardDirection>
          <x>0.00266609015</x>
          <y>-0.64545846</y>
          <z>-0.7637911</z>
        </forwardDirection>
        <ObjectDirectlyAhead>
          <name>Floor</name>
          <position>
            <x>0</x>
            <y>0</y>
            <z>0</z>
          </position>
          <focusPoint>
            <x>18.0241413</x>
            <y>-1.49332967E-16</y>
            <z>6.725359</z>
          </focusPoint>
        </ObjectDirectlyAhead>
      </tracks>
    </Information>
    <Information>
      <totalTimeFacingDirection>0.513567</totalTimeFacingDirection>
      <tracks>
        <startTime>17.0758266</startTime>
        <forwardDirection>
          <x>-0.825807</x>
          <y>-0.3370961</y>
          <z>0.4521162</z>
        </forwardDirection>
        <ObjectDirectlyAhead>
          <name>Floor</name>
          <position>
            <x>0</x>
            <y>0</y>
            <z>0</z>
          </position>
          <focusPoint>
            <x>13.5045233</x>
            <y>-2.306835E-16</y>
            <z>10.389061</z>
          </focusPoint>
        </ObjectDirectlyAhead>
      </tracks>
    </Information>
    <Information>
      <totalTimeFacingDirection>0.5135689</totalTimeFacingDirection>
      <tracks>
        <startTime>17.5893936</startTime>
        <forwardDirection>
          <x>0.096394375</x>
          <y>-0.5446397</y>
          <z>0.833112061</z>
        </forwardDirection>
        <ObjectDirectlyAhead>
          <name>triggerLuzV</name>
          <position>
            <x>17.9</x>
            <y>0.3199978</y>
            <z>8.74</z>
          </position>
          <focusPoint>
            <x>18.05167</x>
            <y>1.17125034</y>
            <z>7.299595</z>
          </focusPoint>
        </ObjectDirectlyAhead>
      </tracks>
    </Information>
    <Information>
      <totalTimeFacingDirection>0.513563156</totalTimeFacingDirection>
      <tracks>
        <startTime>18.1029625</startTime>
        <forwardDirection>
          <x>-0.717484653</x>
          <y>-0.405142456</y>
          <z>0.5666352</z>
        </forwardDirection>
        <ObjectDirectlyAhead>
          <name>Floor</name>
          <position>
            <x>0</x>
            <y>0</y>
            <z>0</z>
          </position>
          <focusPoint>
            <x>15.8879089</x>
            <y>-1.538753E-16</y>
            <z>6.92992735</z>
          </focusPoint>
        </ObjectDirectlyAhead>
      </tracks>
    </Information>
    <Information>
      <totalTimeFacingDirection>0.513565063</totalTimeFacingDirection>
      <tracks>
        <startTime>18.6165257</startTime>
        <forwardDirection>
          <x>-0.33957383</x>
          <y>-0.3762251</y>
          <z>-0.8620581</z>
        </forwardDirection>
        <ObjectDirectlyAhead>
          <name>Floor</name>
          <position>
            <x>0</x>
            <y>0</y>
            <z>0</z>
          </position>
          <focusPoint>
            <x>17.6689377</x>
            <y>-5.037216E-17</y>
            <z>2.26856041</z>
          </focusPoint>
        </ObjectDirectlyAhead>
      </tracks>
    </Information>
    <Information>
      <totalTimeFacingDirection>0.513567</totalTimeFacingDirection>
      <tracks>
        <startTime>19.13009</startTime>
        <forwardDirection>
          <x>0.6020538</x>
          <y>-0.26219</y>
          <z>-0.754179955</z>
        </forwardDirection>
        <ObjectDirectlyAhead>
          <name>Floor</name>
          <position>
            <x>0</x>
            <y>0</y>
            <z>0</z>
          </position>
          <focusPoint>
            <x>23.0653572</x>
            <y>-3.177538E-17</y>
            <z>1.43103588</z>
          </focusPoint>
        </ObjectDirectlyAhead>
      </tracks>
    </Information>
    <Information>
      <totalTimeFacingDirection>0.7786331</totalTimeFacingDirection>
      <tracks>
        <startTime>19.6436577</startTime>
        <forwardDirection>
          <x>0.5546344</x>
          <y>-0.343660563</y>
          <z>-0.757811964</z>
        </forwardDirection>
        <ObjectDirectlyAhead>
          <name>Floor</name>
          <position>
            <x>0</x>
            <y>0</y>
            <z>0</z>
          </position>
          <focusPoint>
            <x>22.9185848</x>
            <y>-2.1328594E-17</y>
            <z>0.9605544</z>
          </focusPoint>
        </ObjectDirectlyAhead>
      </tracks>
    </Information>
    <Information>
      <totalTimeFacingDirection>0.513567</totalTimeFacingDirection>
      <tracks>
        <startTime>20.42229</startTime>
        <forwardDirection>
          <x>0.554279149</x>
          <y>-0.345298976</y>
          <z>-0.7573264</z>
        </forwardDirection>
        <ObjectDirectlyAhead>
          <name>Floor</name>
          <position>
            <x>0</x>
            <y>0</y>
            <z>0</z>
          </position>
          <focusPoint>
            <x>27.4283581</x>
            <y>1.1326874E-16</y>
            <z>-5.10117054</z>
          </focusPoint>
        </ObjectDirectlyAhead>
      </tracks>
    </Information>
    <Information>
      <totalTimeFacingDirection>0.513567</totalTimeFacingDirection>
      <tracks>
        <startTime>20.9358578</startTime>
        <forwardDirection>
          <x>0.542596459</x>
          <y>-0.3502082</y>
          <z>-0.7635074</z>
        </forwardDirection>
        <ObjectDirectlyAhead>
          <name>Floor</name>
          <position>
            <x>0</x>
            <y>0</y>
            <z>0</z>
          </position>
          <focusPoint>
            <x>28.7780838</x>
            <y>1.579629E-16</y>
            <z>-7.11401653</z>
          </focusPoint>
        </ObjectDirectlyAhead>
      </tracks>
    </Information>
    <Information>
      <totalTimeFacingDirection>1.57383347</totalTimeFacingDirection>
      <tracks>
        <startTime>21.4494247</startTime>
        <forwardDirection>
          <x>0.6153189</x>
          <y>-0.325568885</y>
          <z>-0.717904747</z>
        </forwardDirection>
        <ObjectDirectlyAhead>
          <name>Floor</name>
          <position>
            <x>0</x>
            <y>0</y>
            <z>0</z>
          </position>
          <focusPoint>
            <x>31.01924</x>
            <y>2.056875E-16</y>
            <z>-9.263342</z>
          </focusPoint>
        </ObjectDirectlyAhead>
      </tracks>
    </Information>
    <Information>
      <totalTimeFacingDirection>0.513567</totalTimeFacingDirection>
      <tracks>
        <startTime>23.0232582</startTime>
        <forwardDirection>
          <x>0.58588165</x>
          <y>-0.3436605</y>
          <z>-0.73392123</z>
        </forwardDirection>
        <ObjectDirectlyAhead>
          <name>triggerLuzA</name>
          <position>
            <x>33.16</x>
            <y>0.119998932</y>
            <z>-14.0300007</z>
          </position>
          <focusPoint>
            <x>33.618412</x>
            <y>0.9868507</y>
            <z>-12.66588</z>
          </focusPoint>
        </ObjectDirectlyAhead>
      </tracks>
    </Information>
    <Information>
      <totalTimeFacingDirection>1.04372787</totalTimeFacingDirection>
      <tracks>
        <startTime>23.5368252</startTime>
        <forwardDirection>
          <x>0.578867</x>
          <y>-0.3518425</y>
          <z>-0.735608757</z>
        </forwardDirection>
        <ObjectDirectlyAhead>
          <name>triggerLuzA</name>
          <position>
            <x>33.16</x>
            <y>0.119998932</y>
            <z>-14.0300007</z>
          </position>
          <focusPoint>
            <x>33.58645</x>
            <y>0.977543056</y>
            <z>-12.649724</z>
          </focusPoint>
        </ObjectDirectlyAhead>
      </tracks>
    </Information>
    <Information>
      <totalTimeFacingDirection>0.513540268</totalTimeFacingDirection>
      <tracks>
        <startTime>24.5805531</startTime>
        <forwardDirection>
          <x>0.5676898</x>
          <y>-0.3665021</y>
          <z>-0.737160265</z>
        </forwardDirection>
        <ObjectDirectlyAhead>
          <name>triggerLuzA</name>
          <position>
            <x>33.16</x>
            <y>0.119998932</y>
            <z>-14.0300007</z>
          </position>
          <focusPoint>
            <x>33.53866</x>
            <y>0.958481252</y>
            <z>-12.62431</z>
          </focusPoint>
        </ObjectDirectlyAhead>
      </tracks>
    </Information>
    <Information>
      <totalTimeFacingDirection>0.513567</totalTimeFacingDirection>
      <tracks>
        <startTime>25.0940933</startTime>
        <forwardDirection>
          <x>0.435751081</x>
          <y>-0.3939427</y>
          <z>-0.8092773</z>
        </forwardDirection>
        <ObjectDirectlyAhead>
          <name>triggerLuzA</name>
          <position>
            <x>33.16</x>
            <y>0.119998932</y>
            <z>-14.0300007</z>
          </position>
          <focusPoint>
            <x>33.1832161</x>
            <y>1.15319264</y>
            <z>-12.7054739</z>
          </focusPoint>
        </ObjectDirectlyAhead>
      </tracks>
    </Information>
    <Information>
      <totalTimeFacingDirection>0.513567</totalTimeFacingDirection>
      <tracks>
        <startTime>25.60766</startTime>
        <forwardDirection>
          <x>0.212607339</x>
          <y>-0.364877671</y>
          <z>-0.906455934</z>
        </forwardDirection>
        <ObjectDirectlyAhead>
          <name>triggerLuzA</name>
          <position>
            <x>33.16</x>
            <y>0.119998932</y>
            <z>-14.0300007</z>
          </position>
          <focusPoint>
            <x>33.7090454</x>
            <y>1.70680964</y>
            <z>-13.9753923</z>
          </focusPoint>
        </ObjectDirectlyAhead>
      </tracks>
    </Information>
    <Information>
      <totalTimeFacingDirection>0.513565063</totalTimeFacingDirection>
      <tracks>
        <startTime>26.1212273</startTime>
        <forwardDirection>
          <x>-0.94261837</x>
          <y>-0.333807766</y>
          <z>-0.00658098236</z>
        </forwardDirection>
        <ObjectDirectlyAhead>
          <name>Floor</name>
          <position>
            <x>0</x>
            <y>0</y>
            <z>0</z>
          </position>
          <focusPoint>
            <x>27.6332684</x>
            <y>3.2678412E-16</y>
            <z>-14.7170467</z>
          </focusPoint>
        </ObjectDirectlyAhead>
      </tracks>
    </Information>
    <Information>
      <totalTimeFacingDirection>0.513565063</totalTimeFacingDirection>
      <tracks>
        <startTime>26.6347923</startTime>
        <forwardDirection>
          <x>0.3334111</x>
          <y>-0.4632969</y>
          <z>0.8210926</z>
        </forwardDirection>
        <ObjectDirectlyAhead>
          <name>triggerLuzA</name>
          <position>
            <x>33.16</x>
            <y>0.119998932</y>
            <z>-14.0300007</z>
          </position>
          <focusPoint>
            <x>32.7177658</x>
            <y>1.67768955</y>
            <z>-14.4776945</z>
          </focusPoint>
        </ObjectDirectlyAhead>
      </tracks>
    </Information>
    <Information>
      <totalTimeFacingDirection>0.513567</totalTimeFacingDirection>
      <tracks>
        <startTime>27.1483574</startTime>
        <forwardDirection>
          <x>-0.9270573</x>
          <y>-0.3189603</y>
          <z>0.197051749</z>
        </forwardDirection>
        <ObjectDirectlyAhead>
          <name>Floor</name>
          <position>
            <x>0</x>
            <y>0</y>
            <z>0</z>
          </position>
          <focusPoint>
            <x>27.4734268</x>
            <y>3.01183952E-16</y>
            <z>-13.5641193</z>
          </focusPoint>
        </ObjectDirectlyAhead>
      </tracks>
    </Information>
    <Information>
      <totalTimeFacingDirection>0.513567</totalTimeFacingDirection>
      <tracks>
        <startTime>27.6619244</startTime>
        <forwardDirection>
          <x>-0.949124455</x>
          <y>-0.3106774</y>
          <z>-0.0514028259</z>
        </forwardDirection>
        <ObjectDirectlyAhead>
          <name>Floor</name>
          <position>
            <x>0</x>
            <y>0</y>
            <z>0</z>
          </position>
          <focusPoint>
            <x>24.56205</x>
            <y>3.32669014E-16</y>
            <z>-14.9820814</z>
          </focusPoint>
        </ObjectDirectlyAhead>
      </tracks>
    </Information>
    <Information>
      <totalTimeFacingDirection>1.12653351</totalTimeFacingDirection>
      <tracks>
        <startTime>28.1754913</startTime>
        <forwardDirection>
          <x>-0.9497069</x>
          <y>-0.3023709</y>
          <z>-0.08141895</z>
        </forwardDirection>
        <ObjectDirectlyAhead>
          <name>Floor</name>
          <position>
            <x>0</x>
            <y>0</y>
            <z>0</z>
          </position>
          <focusPoint>
            <x>21.9198</x>
            <y>3.41642957E-16</y>
            <z>-15.38623</z>
          </focusPoint>
        </ObjectDirectlyAhead>
      </tracks>
    </Information>
    <Information>
      <totalTimeFacingDirection>0.513567</totalTimeFacingDirection>
      <tracks>
        <startTime>29.3020248</startTime>
        <forwardDirection>
          <x>-0.952487946</x>
          <y>-0.302370846</y>
          <z>-0.0365911722</z>
        </forwardDirection>
        <ObjectDirectlyAhead>
          <name>Floor</name>
          <position>
            <x>0</x>
            <y>0</y>
            <z>0</z>
          </position>
          <focusPoint>
            <x>15.8802462</x>
            <y>3.45747732E-16</y>
            <z>-15.5710926</z>
          </focusPoint>
        </ObjectDirectlyAhead>
      </tracks>
    </Information>
    <Information>
      <totalTimeFacingDirection>4.464407</totalTimeFacingDirection>
      <tracks>
        <startTime>29.8155918</startTime>
        <forwardDirection>
          <x>-0.952906</x>
          <y>-0.3023709</y>
          <z>-0.0232888442</z>
        </forwardDirection>
        <ObjectDirectlyAhead>
          <name>Floor</name>
          <position>
            <x>0</x>
            <y>0</y>
            <z>0</z>
          </position>
          <focusPoint>
            <x>13.3812132</x>
            <y>3.47263233E-16</y>
            <z>-15.6393452</z>
          </focusPoint>
        </ObjectDirectlyAhead>
      </tracks>
    </Information>
  </LookData>
</UserLog>